sksurgerynditracker/__init__.py
sksurgerynditracker/_version.py
sksurgerynditracker/demo.py
sksurgerynditracker/nditracker.py
scikit_surgerynditracker-0.1.7.dist-info/LICENSE
scikit_surgerynditracker-0.1.7.dist-info/METADATA
scikit_surgerynditracker-0.1.7.dist-info/WHEEL
scikit_surgerynditracker-0.1.7.dist-info/top_level.txt
scikit_surgerynditracker-0.1.7.dist-info/RECORD
