Metadata-Version: 2.1
Name: scikit-surgerynditracker
Version: 0.1.7
Summary: Interface for Northern Digital (NDI) Trackers with data to NumPy arrays
Home-page: https://weisslab.cs.ucl.ac.uk/WEISS/SoftwareRepositories/SNAPPY/scikit-surgerynditracker
Author: Stephen Thompson
Author-email: s.thompson@ucl.ac.uk
License: BSD-3 license
Keywords: medical imaging
Platform: UNKNOWN
Classifier: Development Status :: 3 - Alpha
Classifier: Intended Audience :: Developers
Classifier: Intended Audience :: Education
Classifier: Intended Audience :: Healthcare Industry
Classifier: Intended Audience :: Information Technology
Classifier: Intended Audience :: Science/Research
Classifier: License :: OSI Approved :: BSD License
Classifier: Programming Language :: Python
Classifier: Programming Language :: Python :: 2
Classifier: Programming Language :: Python :: 3
Classifier: Topic :: Scientific/Engineering :: Information Analysis
Classifier: Topic :: Scientific/Engineering :: Medical Science Apps.
Classifier: Topic :: System :: Hardware
Requires-Dist: six (>=1.10)
Requires-Dist: numpy (>=1.11)
Requires-Dist: ndicapi (>=3.2.6)
